edgex_python_sdk-0.2.0.dist-info/licenses/LICENSE
edgex_sdk/__init__.py
edgex_sdk/client.py
edgex_sdk/account/__init__.py
edgex_sdk/account/client.py
edgex_sdk/asset/__init__.py
edgex_sdk/asset/client.py
edgex_sdk/crypto/__init__.py
edgex_sdk/crypto/constants.py
edgex_sdk/crypto/pedersen_hash.py
edgex_sdk/funding/__init__.py
edgex_sdk/funding/client.py
edgex_sdk/internal/__init__.py
edgex_sdk/internal/async_client.py
edgex_sdk/internal/client.py
edgex_sdk/internal/signing_adapter.py
edgex_sdk/internal/starkex_signing_adapter.py
edgex_sdk/metadata/__init__.py
edgex_sdk/metadata/client.py
edgex_sdk/order/__init__.py
edgex_sdk/order/client.py
edgex_sdk/order/types.py
edgex_sdk/quote/__init__.py
edgex_sdk/quote/client.py
edgex_sdk/transfer/__init__.py
edgex_sdk/transfer/client.py
edgex_sdk/ws/__init__.py
edgex_sdk/ws/client.py
edgex_sdk/ws/manager.py
scripts/build_and_test_package.py
edgex_python_sdk-0.2.0.dist-info/METADATA
edgex_python_sdk-0.2.0.dist-info/WHEEL
edgex_python_sdk-0.2.0.dist-info/top_level.txt
edgex_python_sdk-0.2.0.dist-info/RECORD
