Metadata-Version: 2.4
Name: edgex-python-sdk
Version: 0.2.0
Summary: A Python SDK for interacting with the EdgeX Exchange API
Home-page: https://github.com/edgex-Tech/edgex-python-sdk
Author: EdgeX Tech
Author-email: EdgeX Tech <info@edgex.exchange>
Maintainer-email: EdgeX Tech <info@edgex.exchange>
License: MIT
Project-URL: Homepage, https://github.com/edgex-Tech/edgex-python-sdk
Project-URL: Repository, https://github.com/edgex-Tech/edgex-python-sdk
Project-URL: Documentation, https://github.com/edgex-Tech/edgex-python-sdk#readme
Project-URL: Bug Reports, https://github.com/edgex-Tech/edgex-python-sdk/issues
Keywords: edgex,exchange,trading,api,sdk,cryptocurrency
Classifier: Development Status :: 3 - Alpha
Classifier: Intended Audience :: Developers
Classifier: License :: OSI Approved :: MIT License
Classifier: Programming Language :: Python :: 3
Classifier: Programming Language :: Python :: 3.7
Classifier: Programming Language :: Python :: 3.8
Classifier: Programming Language :: Python :: 3.9
Classifier: Programming Language :: Python :: 3.10
Classifier: Programming Language :: Python :: 3.11
Classifier: Topic :: Software Development :: Libraries :: Python Modules
Classifier: Topic :: Internet :: WWW/HTTP :: Dynamic Content
Classifier: Topic :: Office/Business :: Financial
Requires-Python: >=3.7
License-File: LICENSE
Requires-Dist: aiohttp>=3.8.0
Requires-Dist: websocket-client>=1.0.0
Requires-Dist: pydantic>=1.8.0
Requires-Dist: python-dotenv>=0.15.0
Requires-Dist: pycryptodome>=3.15.0
Requires-Dist: ecdsa>=0.17.0
Provides-Extra: dev
Requires-Dist: pytest>=6.0; extra == "dev"
Requires-Dist: pytest-asyncio>=0.18.0; extra == "dev"
Requires-Dist: black>=21.0.0; extra == "dev"
Requires-Dist: flake8>=3.8.0; extra == "dev"
Requires-Dist: mypy>=0.800; extra == "dev"
Dynamic: author
Dynamic: home-page
Dynamic: license-file
Dynamic: requires-python
